<?xml version="1.0"?>
<job_config>
  <input>
    <video>
      <mxf version="1">
        <file_name>FILE_NAME</file_name>    <!-- string -->
        <storage>
          <local>
            <path>PATH</path>    <!-- string -->
          </local>
        </storage>
      </mxf>
    </video>
  </input>
  <filter>
    <video>
      <dv_mezz_to_dv_profile_5 version="2">
        <start>0</start>    <!-- string -->
        <end>0</end>    <!-- string -->
        <metadata_offset>0</metadata_offset>    <!-- integer -->
        <active_area_offset_top>-1</active_area_offset_top>    <!-- integer -->
        <active_area_offset_bottom>-1</active_area_offset_bottom>    <!-- integer -->
        <active_area_offset_left>-1</active_area_offset_left>    <!-- integer -->
        <active_area_offset_right>-1</active_area_offset_right>    <!-- integer -->
        <signal_range_coded>auto</signal_range_coded>    <!-- One of: auto, computer, video, signal -->
        <decoder_parallel_frames>0</decoder_parallel_frames>    <!-- integer: from 0 to 16 -->
        <prepend_frames>0</prepend_frames>    <!-- integer -->
        <append_frames>0</append_frames>    <!-- integer -->
        <target_width>0</target_width>    <!-- integer list -->
        <target_height>0</target_height>    <!-- integer list -->
        <max_scene_frames>240</max_scene_frames>    <!-- integer: from 12 to 256 -->
        <preprocessing_mode>optimized</preprocessing_mode>    <!-- One of: optimized, standard -->
        <data_rate>16000</data_rate>    <!-- integer list -->
        <max_vbv_data_rate>16000</max_vbv_data_rate>    <!-- integer list -->
        <vbv_buffer_size>32000</vbv_buffer_size>    <!-- integer list -->
        <encode_pass_num>2</encode_pass_num>    <!-- integer -->
        <disable_md_postproc>false</disable_md_postproc>    <!-- boolean: true or false -->
        <max_cll>-1</max_cll>    <!-- integer: from -1 to 65535 -->
        <max_fall>-1</max_fall>    <!-- integer: from -1 to 65535 -->
        <prepend_frames_method>1</prepend_frames_method>    <!-- integer: from 0 to 1 -->
        <append_frames_method>1</append_frames_method>    <!-- integer: from 0 to 1 -->
        <decoder>
          <j2k_dec>
            <kakadu_dlb/>    <!-- If plugin 'kakadu_dlb' is not available use the other one, e.g. 'base'. -->
          </j2k_dec>
        </decoder>
        <scaling>
          <base>
            <source_crop_top>0</source_crop_top>    <!-- integer -->
            <source_crop_bottom>0</source_crop_bottom>    <!-- integer -->
            <source_crop_left>0</source_crop_left>    <!-- integer -->
            <source_crop_right>0</source_crop_right>    <!-- integer -->
          </base>
        </scaling>
        <noise>
          <base>
            <strength>0</strength>    <!-- fixed value -->
          </base>
        </noise>
        <hevc_enc>
          <ffmpeg>
            <ffmpeg_bin>/absolute/path/to/ffmpeg</ffmpeg_bin>    <!-- string -->
            <cmd_gen>/absolute/path/to/cmd_gen_hevc_enc_ffmpeg.py</cmd_gen>    <!-- string -->
            <user_params_file>/absolute/path/to/profile_5.json</user_params_file>    <!-- string -->
            <interpreter>python</interpreter>    <!-- string -->
            <redirect_stdout>false</redirect_stdout>    <!-- boolean: true or false -->
          </ffmpeg>
        </hevc_enc>
      </dv_mezz_to_dv_profile_5>
    </video>
  </filter>
  <output>
    <hevc version="1">
      <file_name>FILE_NAME</file_name>    <!-- string list -->
      <storage>
        <local>
          <path>PATH</path>    <!-- string -->
        </local>
      </storage>
    </hevc>
  </output>
  <misc>
    <temp_dir>
      <clean_temp>true</clean_temp>
      <path>PATH</path>
    </temp_dir>
  </misc>
</job_config>
